LICENSE
MANIFEST.in
README.md
setup.py
docs/images/demo.png
docs/images/entry_attributes.png
docs/images/field_attributes.png
docs/images/group.png
docs/images/simplest_example.png
docs/images/theme.png
pypick/__init__.py
pypick/pick.py
pypick/ui.py
pypick.egg-info/PKG-INFO
pypick.egg-info/SOURCES.txt
pypick.egg-info/dependency_links.txt
pypick.egg-info/requires.txt
pypick.egg-info/top_level.txt