Metadata-Version: 2.1
Name: pypick
Version: 0.2.0
Summary: A module for selecting an item from a list of multi-field data in terminal
Home-page: https://github.com/rayx/pypick
Author: Huan Xiong
Author-email: huan.xiong@outlook.com
License: GPLv3+
Platform: unix-like
Classifier: Development Status :: 4 - Beta
Classifier: License :: OSI Approved :: GNU General Public License v3 or later (GPLv3+)
Classifier: Intended Audience :: Developers
Classifier: Topic :: Software Development :: Libraries :: Python Modules
Classifier: Environment :: Console
Classifier: Operating System :: POSIX
Classifier: Operating System :: Unix
Classifier: Operating System :: MacOS :: MacOS X
Classifier: Programming Language :: Python :: 3
Classifier: Programming Language :: Python :: 3.5
Classifier: Programming Language :: Python :: 3.6
Classifier: Programming Language :: Python :: 3.7
